[{"timestamp":"2023-09-01T00:21:17.165Z","count":17,"uniques":7},{"timestamp":"2023-10-01T06:06:47.234Z","count":58,"uniques":8},{"timestamp":"2023-11-01T18:06:26.970Z","count":43,"uniques":11},{"timestamp":"2023-12-01T06:06:06.423Z","count":73,"uniques":9},{"timestamp":"2024-01-01T06:07:24.724Z","count":21,"uniques":8},{"timestamp":"2024-02-01T00:18:16.615Z","count":35,"uniques":6},{"timestamp":"2024-03-01T06:06:07.475Z","count":22,"uniques":8},{"timestamp":"2024-04-01T00:19:12.535Z","count":49,"uniques":6},{"timestamp":"2024-05-01T00:19:19.613Z","count":30,"uniques":17},{"timestamp":"2024-06-01T00:23:46.899Z","count":18,"uniques":7},{"timestamp":"2024-07-01T18:06:47.967Z","count":95,"uniques":12},{"timestamp":"2024-08-01T06:08:08.212Z","count":102,"uniques":10},{"timestamp":"2024-09-01T18:07:07.164Z","count":1,"uniques":1}]
