[{"timestamp":"2023-11-15T00:17:55.800Z","count":0,"uniques":0},{"timestamp":"2023-11-16T00:18:13.014Z","count":0,"uniques":0},{"timestamp":"2023-11-17T00:17:53.919Z","count":0,"uniques":0},{"timestamp":"2023-11-18T00:17:39.268Z","count":0,"uniques":0},{"timestamp":"2023-11-19T00:19:39.863Z","count":0,"uniques":0},{"timestamp":"2023-11-20T06:06:02.042Z","count":0,"uniques":0},{"timestamp":"2023-11-21T00:18:27.181Z","count":0,"uniques":0},{"timestamp":"2023-11-22T00:18:44.883Z","count":0,"uniques":0},{"timestamp":"2023-11-23T00:18:22.967Z","count":0,"uniques":0},{"timestamp":"2023-11-24T00:17:42.156Z","count":0,"uniques":0},{"timestamp":"2023-11-25T00:17:22.138Z","count":0,"uniques":0},{"timestamp":"2023-11-26T00:19:37.176Z","count":0,"uniques":0},{"timestamp":"2023-11-27T00:18:34.299Z","count":0,"uniques":0},{"timestamp":"2023-11-28T00:18:13.026Z","count":0,"uniques":0},{"timestamp":"2023-11-29T00:18:38.570Z","count":0,"uniques":0},{"timestamp":"2023-11-30T00:18:21.702Z","count":0,"uniques":0},{"timestamp":"2023-12-01T00:00:00.000Z","count":4,"uniques":1},{"timestamp":"2023-12-02T00:17:38.036Z","count":0,"uniques":0},{"timestamp":"2023-12-03T00:19:49.199Z","count":0,"uniques":0},{"timestamp":"2023-12-04T00:18:50.389Z","count":0,"uniques":0},{"timestamp":"2023-12-05T00:18:20.357Z","count":0,"uniques":0},{"timestamp":"2023-12-06T00:00:00.000Z","count":2,"uniques":1},{"timestamp":"2023-12-07T00:00:00.000Z","count":2,"uniques":1},{"timestamp":"2023-12-08T00:18:28.954Z","count":0,"uniques":0},{"timestamp":"2023-12-09T00:18:09.727Z","count":0,"uniques":0},{"timestamp":"2023-12-10T00:20:07.472Z","count":0,"uniques":0},{"timestamp":"2023-12-11T00:18:59.806Z","count":0,"uniques":0},{"timestamp":"2023-12-12T00:18:40.754Z","count":0,"uniques":0},{"timestamp":"2023-12-13T00:18:20.219Z","count":0,"uniques":0},{"timestamp":"2023-12-14T00:18:16.257Z","count":0,"uniques":0},{"timestamp":"2023-12-15T00:00:00.000Z","count":2,"uniques":1}]
